{"format_version":"1.10.0","animations":{"animation.crossbow.wield_first_person":{"loop":true,"bones":{"rightitem":{"rotation":[-9,60,-47],"position":[13,7,2]},"firework":{"rotation":[157.6,57.8,-54.7],"position":[1.8,3.25,1.5],"scale":0.75}}},"animation.crossbow.wield_third_person":{"loop":true,"bones":{"rightitem":{"rotation":[0,-3,3.25],"position":[0.5,-0.5,-1.5]},"firework":{"rotation":[177,-3.6,-0.6],"position":[0.85,1.5,-5.15],"scale":0.75}}},"animation.crossbow.charging":{"animation_length":2,"bones":{"rightitem":{"rotation":{"0.0":["math.cos(q.anim_time*1800)*3","math.sin(q.anim_time*1800)*10",0],"0.5":[0,0,0]},"position":{"0.0":[0,0,0],"1.0":[0,0,"-math.sin(q.anim_time*1800)*0.3"]},"scale":{"0.0":[1,1,1],"1.0":["1-math.sin(q.anim_time*1800)*0.02","1+math.sin(q.anim_time*1800)*0.02",1]}}}}}}