{"format_version":"1.8.0","animations":{"animation.turtle.crawl":{"loop":true,"anim_time_update":"query.modified_distance_moved*(q.is_baby?5:1)","bones":{"root":{"position":[0,0,"-math.sin(query.anim_time*73.2)*2.5"]},"build":{"rotation":["-math.cos(q.anim_time*73.2)*5","-math.sin(q.anim_time*36.6)*12","math.cos(q.anim_time*36.6)*8"],"position":[0,"0.5-math.sin(q.anim_time*73.2)*0.4",0]},"FR_leg":{"rotation":[0,"-math.sin(query.anim_time*36.6)*60",0],"position":["math.cos(query.anim_time*73.2)*2.7","-2+math.max(math.cos(query.anim_time*36.6)*4,0)","-1+math.sin(query.anim_time*36.6)*2"]},"head":{"rotation":["-math.cos(q.anim_time*73.2-45)*5","math.sin(q.anim_time*36.6-45)*12","math.cos(q.anim_time*36.6+45)*8"]},"FL_leg":{"rotation":[0,"-math.sin(query.anim_time*36.6)*60",0],"position":["-math.cos(query.anim_time*73.2)*2.7","-2+math.max(-math.cos(query.anim_time*36.6)*4,0)","-1-math.sin(query.anim_time*36.6)*2"]},"IK_FL_leg":{"rotation":[0,0,"10+math.cos(query.anim_time*36.6)*10"]},"IK_RL_leg":{"rotation":[0,0,"-10+math.cos(query.anim_time*36.6)*10"]},"BL_leg":{"rotation":["-10+math.cos(q.anim_time*73.2-45)*6","-3+math.sin(q.anim_time*36.6)*8",0],"position":["-math.sin(q.anim_time*36.6)*2","0.5-math.cos(q.anim_time*73.2-45)","math.sin(q.anim_time*36.6)"]},"BR_leg":{"rotation":["-10+math.cos(q.anim_time*73.2)*6","3+math.sin(q.anim_time*36.6)*8",0],"position":["-math.sin(q.anim_time*36.6)*2","0.5-math.cos(q.anim_time*73.2)","-math.sin(q.anim_time*36.6)"]}}},"animation.turtle.swim":{"loop":true,"anim_time_update":"q.anim_time+q.delta_time*(q.is_baby?1.5:1)","bones":{"root":{"rotation":["-math.cos(q.anim_time*200)*10",0,0],"position":[0,"math.sin(q.anim_time*200)*2.5",0]},"head":{"rotation":["math.sin(q.anim_time*200)*20",0,0]},"FR_leg":{"rotation":["-math.sin(q.anim_time*200)*20","-math.sin(q.anim_time*200-45)*35","-math.cos(q.anim_time*200)*45"],"position":["-2+math.sin(q.anim_time*200)","1+math.sin(q.anim_time*200)*2",-4]},"FL_leg":{"rotation":["-math.sin(q.anim_time*200)*20","math.sin(q.anim_time*200-45)*35","math.cos(q.anim_time*200)*45"],"position":["2-math.sin(q.anim_time*200)","1+math.sin(q.anim_time*200)*2",-4]},"BR_leg":{"rotation":["-math.cos(q.anim_time*200-22.5)*20",0,0]},"BL_leg":{"rotation":["-math.cos(q.anim_time*200-22.5)*20",0,0]}}},"animation.turtle.float":{"loop":true,"bones":{"root":{"rotation":["math.sin(query.anim_time*120)*3",0,"math.cos(query.anim_time*60)*4"],"position":[0,"math.cos(query.anim_time*120)*0.4",0]},"head":{"rotation":["math.cos(query.anim_time*120)*3",0,"math.sin(query.anim_time*60)*4"]},"FR_leg":{"rotation":["math.sin(query.anim_time*60)*8",0,"math.cos(query.anim_time*60)*5"]},"FL_leg":{"rotation":["math.sin(query.anim_time*60)*8",0,"-math.cos(query.anim_time*60)*5"]},"BR_leg":{"rotation":["math.sin(query.anim_time*120-45)*6",0,"math.sin(query.anim_time*60)*6"]},"BL_leg":{"rotation":["math.sin(query.anim_time*120-45)*6",0,"-math.sin(query.anim_time*60)*6"]}}},"animation.turtle.target":{"loop":true,"bones":{"head":{"rotation":["q.target_x_rotation-q.body_x_rotation","-math.sin(q.target_y_rotation*2)*60",0]},"pupils":{"position":[0,0,"math.min(math.abs(q.target_y_rotation/45),1)"]},"root":{"rotation":["q.body_x_rotation",0,0]}}},"animation.turtle.baby_setup":{"loop":"hold_on_last_frame","bones":{"build":{"position":[0,2,-0.3],"scale":6.66},"head":{"position":[0,0,7],"scale":0.833},"FR_leg":{"position":[-5,0,0.75],"scale":6.66},"IK_RL_leg":{"rotation":[0,0,"this"]},"FL_leg":{"position":[5,0,0.75],"scale":6.66},"IK_FL_leg":{"rotation":[0,0,"this"]},"BR_leg":{"rotation":[-10,0,0],"position":[-3,3.25,3.75],"scale":6.66},"BL_leg":{"rotation":[-10,0,0],"position":[3,3.25,3.75],"scale":6.66}}},"animation.turtle.bob_0":{"loop":true,"anim_time_update":"q.anim_time+q.delta_time*(q.is_baby?2:1)","blend_weight":"q.is_baby?2:1","bones":{"build":{"rotation":["math.sin(q.anim_time*90)",0,0]},"head":{"rotation":["-math.cos(q.anim_time*90)*2","math.cos(q.anim_time*45)*2","-math.sin(q.anim_time*45)*2"]},"IK_RL_leg":{"rotation":[0,0,"math.sin(q.anim_time*90)"]},"IK_FL_leg":{"rotation":[0,0,"-math.sin(q.anim_time*90)"]}}},"animation.turtle.fall":{"loop":"hold_on_last_frame","animation_length":0.6667,"bones":{"root":{"position":{"0.0":[0,0,0],"0.0667":[0,-0.12812,0],"0.1333":[0,-0.51904,0],"0.2667":[0,-2.02161,0],"0.4":[0,-3.97839,0],"0.5333":[0,-5.48096,0],"0.6":[0,-5.87188,0],"0.6667":[0,-6,0]}},"head":{"rotation":{"0.0":[0,0,0],"0.0667":[-3.78294,0,0],"0.1333":[-15.05009,0,0],"0.2":[-29.94991,0,0],"0.2667":[-41.21706,0,0],"0.3333":[-45,0,0],"0.4":[-41.21738,0,0],"0.4667":[-29.95228,0,0],"0.5333":[-15.05482,0,0],"0.6":[-3.78645,0,0],"0.6667":[0,0,0]}},"FR_leg":{"rotation":{"0.0":[0,0,0],"0.1333":[0,0,-6.40841],"0.2667":[0,0,-23.92117],"0.4":[0,0,-46.07883],"0.5333":[0,0,-63.59159],"0.6667":[0,0,-70]},"position":{"0.0":[0,0,0],"0.1333":[-0.1831,-0.55703,0],"0.2667":[-0.68346,-2.05734,0],"0.4":[-1.31654,-3.94266,0],"0.5333":[-1.8169,-5.44297,0],"0.6667":[-2,-6,0]}},"FL_leg":{"rotation":{"0.0":[0,0,0],"0.1333":[0,0,6.40841],"0.2667":[0,0,23.92117],"0.4":[0,0,46.07883],"0.5333":[0,0,63.59159],"0.6667":[0,0,70]},"position":{"0.0":[0,0,0],"0.1333":[0.1831,-0.55703,0],"0.2667":[0.68346,-2.05734,0],"0.4":[1.31654,-3.94266,0],"0.5333":[1.8169,-5.44297,0],"0.6667":[2,-6,0]}},"BR_leg":{"rotation":{"0.0":[0,0,0],"0.1333":[6.76961,0,0],"0.2667":[25.54167,0,0],"0.4":[49.45833,0,0],"0.5333":[68.23039,0,0],"0.6667":[75,0,0]},"position":{"0.0":[0,0,0],"0.1333":[0,1.37817,-0.68043],"0.2667":[0,4.31496,-2.15179],"0.4":[0,7.68504,-3.84821],"0.5333":[0,10.62183,-5.31957],"0.6667":[0,12,-6]}},"BL_leg":{"rotation":{"0.0":[0,0,0],"0.1333":[6.76961,0,0],"0.2667":[25.54167,0,0],"0.4":[49.45833,0,0],"0.5333":[68.23039,0,0],"0.6667":[75,0,0]},"position":{"0.0":[0,0,0],"0.1333":[0,1.37817,-0.68043],"0.2667":[0,4.31496,-2.15179],"0.4":[0,7.68504,-3.84821],"0.5333":[0,10.62183,-5.31957],"0.6667":[0,12,-6]}},"build":{"rotation":{"0.0":[0,0,0],"0.0667":[4.84607,0,0],"0.2":[25.57663,0,0],"0.4":[60.95983,0,0],"0.5333":[73.8,0,0],"0.6667":[80,0,0]}}}},"animation.turtle.jump":{"loop":"hold_on_last_frame","animation_length":0.7667,"bones":{"build":{"rotation":{"0.0":[0,0,0],"0.2667":[-20,0,0]},"position":{"0.0":[0,0,0],"0.2667":[0,0,0]}},"centroid":{"rotation":{"0.0":[0,0,0],"0.0667":[-42.75,0,0],"0.1":[-48.6,0,0],"0.1333":[-49.73,0,0],"0.1667":[-47.87,0,0],"0.2333":[-35,0,0],"0.3":[-24,0,0],"0.4":[-15.14,0,0],"0.5333":[-9.46,0,0],"0.6667":[-7.09,0,0],"0.7667":[-6.8,0,0]},"position":{"0.0":[0,0,0],"0.0667":[0,-1.45,0],"0.1333":[0,-2,0],"0.2":[0,-2.05,0],"0.2667":[0,-1.85,0],"0.5":[0,-0.55,0],"0.6":[0,-0.2,0],"0.7":[0,-0.03,0],"0.7667":[0,0,0]}},"FR_leg":{"rotation":{"0.0":[0,0,0],"0.0667":[0,0,-37.63541],"0.1":[0,0,-43.339],"0.1333":[0,0,-45],"0.1667":[0,0,-44.17302],"0.2333":[0,0,-38.12366],"0.3":[0,0,-29.37634],"0.3667":[0,0,-23.32698],"0.4":[0,0,-22.5]},"position":{"0.0667":[0,0,0],"0.1333":[0,0.61097,0],"0.2":[0,2.38903,0],"0.2667":[0,3,0],"0.3333":[0,2.79634,0],"0.4":[0,2.20366,0],"0.4667":[0,2,0]}},"FL_leg":{"rotation":{"0.0":[0,0,0],"0.0667":[0,0,37.63541],"0.1":[0,0,43.339],"0.1333":[0,0,45],"0.1667":[0,0,44.17302],"0.2333":[0,0,38.12366],"0.3":[0,0,29.37634],"0.3667":[0,0,23.32698],"0.4":[0,0,22.5]},"position":{"0.0667":[0,0,0],"0.1333":[0,0.61097,0],"0.2":[0,2.38903,0],"0.2667":[0,3,0],"0.3333":[0,2.79634,0],"0.4":[0,2.20366,0],"0.4667":[0,2,0]}},"BR_leg":{"rotation":{"0.0":[0,0,0],"0.2667":[-45,0,0]},"position":{"0.0":[0,0,0],"0.1667":[0,-5.1,0],"0.2":[0,-5.8,0],"0.2333":[0,-6.2,0],"0.2667":[0,-5.9,0],"0.3333":[0,-4.3,0],"0.4":[0,-3.35,0],"0.5":[0,-2.5,0],"0.6333":[0,-2.25,0]}},"BL_leg":{"rotation":{"0.0":[0,0,0],"0.2667":[-45,0,0]},"position":{"0.0":[0,0,0],"0.1667":[0,-5.1,0],"0.2":[0,-5.8,0],"0.2333":[0,-6.2,0],"0.2667":[0,-5.9,0],"0.3333":[0,-4.3,0],"0.4":[0,-3.35,0],"0.5":[0,-2.5,0],"0.6333":[0,-2.25,0]}}}},"animation.turtle.land":{"animation_length":0.625,"bones":{"head":{"rotation":{"0.0":[0,0,0],"0.125":[-13.5,0,0],"0.1875":[-7.475,0,0],"0.25":[11.225,0,0],"0.3125":[18.2,0,0],"0.375":[20.1125,0,0],"0.4375":[15.8,0,0],"0.5":[6.2,0,0],"0.5625":[1.125,0,0],"0.625":[0,0,0]},"position":{"0.0":[0,0,0],"0.0625":[0,-0.3,0],"0.125":[0,-1.05,0],"0.1875":[0,-1.6,0],"0.25":[0,-1.75,0],"0.3125":[0,-1.65,0],"0.375":[0,-1.2,0],"0.4375":[0,-0.525,0],"0.5":[0,-0.15,0],"0.5625":[0,0,0]}},"IK_RL_leg":{"rotation":{"0.0":[0,0,0],"0.0625":[0,0,-2.40074],"0.0938":[0,0,-2.5],"0.125":[0,0,-2.20758],"0.1563":[0,0,-1.06412],"0.2188":[0,0,3.56412],"0.25":[0,0,4.70758],"0.2813":[0,0,5],"0.3125":[0,0,4.84295],"0.375":[0,0,3.7372],"0.4688":[0,0,1.2628],"0.5313":[0,0,0.15705],"0.5625":[0,0,0]}},"IK_FL_leg":{"rotation":{"0.0":[0,0,0],"0.0625":[0,0,2.40074],"0.0938":[0,0,2.5],"0.125":[0,0,2.20758],"0.1563":[0,0,1.06412],"0.2188":[0,0,-3.56412],"0.25":[0,0,-4.70758],"0.2813":[0,0,-5],"0.3125":[0,0,-4.84295],"0.375":[0,0,-3.7372],"0.4688":[0,0,-1.2628],"0.5313":[0,0,-0.15705],"0.5625":[0,0,0]}},"BR_leg":{"rotation":{"0.0":[0,0,0],"0.125":[13.5,0,0],"0.1875":[7.475,0,0],"0.25":[-11.225,0,0],"0.3125":[-18.2,0,0],"0.375":[-20.1125,0,0],"0.4375":[-15.8,0,0],"0.5":[-6.2,0,0],"0.5625":[-1.125,0,0],"0.625":[0,0,0]}},"BL_leg":{"rotation":{"0.0":[0,0,0],"0.125":[13.5,0,0],"0.1875":[7.475,0,0],"0.25":[-11.225,0,0],"0.3125":[-18.2,0,0],"0.375":[-20.1125,0,0],"0.4375":[-15.8,0,0],"0.5":[-6.2,0,0],"0.5625":[-1.125,0,0],"0.625":[0,0,0]}},"root":{"scale":{"0.0625":[1,1,1],"0.125":[1.00479,0.99043,1.00479],"0.1875":[1.02021,0.95957,1.02021],"0.25":[1.025,0.95,1.025],"0.3125":[1.02231,0.95539,1.02231],"0.5":[1.00269,0.99461,1.00269],"0.5625":[1,1,1]}}}},"animation.turtle.vert_cap":{"loop":true,"bones":{"root":{"position":[0,0,"-this"]}}}}}